{
    "class": {
        "name": "Barbare",
        "description": "Le barbare est un combattant sauvage issu d’une culture primitive. Il affronte ses ennemis avec rage sans se cacher derrière une lourde armure.",
        "imageUrl": "https://www.co-drs.org/sites/default/files/styles/original_compressed/public/co/profile/2023-02/barbarian.png.webp?itok=dHQHS0Ze",
        "stats": {
            "hpPerLevel": 5,
            "profileType": "Combattant au contact / Tank (PV)",
            "hitDie": "1D12"
        },
        "lore": {
            "terres_d_osgild": "On trouve quelques clans de rudes montagnards qui vivent dans les monts Vierges à l’ouest de Clairval et de la forêt de Myrviel. Ils sont en guerre incessante contre les humanoïdes du désert de Krön.",
            "origines_possibles": [
                "Montagnards des Monts Vierges",
                "Tribus de la jungle de Luir‑An‑Doral (elfes, humains, orcs)",
                "Royaumes barbares du nord"
            ]
        }
    },
    "masteries": {
        "weapons": "Le barbare sait manier toutes les armes au contact, toutes les armes à distance (sauf les arbalètes et les armes d'une technologie trop complexe).",
        "armors": "Les voies de barbare limitent l'armure au cuir renforcé.",
        "shields": "Le barbare peut en revanche utiliser tous les boucliers.",
        "evolution_armure": "Certaines capacités (Voie de la Brute) permettent de débloquer le port d'armures plus lourdes."
    },
    "startingEquipment": [
        {
            "choice": [
                {
                    "item": "Hache à deux mains",
                    "stats": "DM 2d6"
                },
                {
                    "set": [
                        {
                            "item": "Arme à une main",
                            "stats": "DM 1d8"
                        },
                        {
                            "item": "Bouclier",
                            "stats": "DEF +2"
                        }
                    ]
                }
            ]
        },
        {
            "item": "2 javelots",
            "stats": "DM 1d6, portée 20 m"
        },
        {
            "item": "Dague",
            "stats": "DM 1d4"
        },
        {
            "item": "Armure de cuir",
            "stats": "DEF +2"
        }
    ],
    "paths": [
        {
            "name": "Voie de la Brute",
            "abilities": [
                {
                    "rank": 1,
                    "name": "Argument de taille",
                    "type": "Passif",
                    "description": "Le barbare ajoute sa FOR à son maximum de PV ainsi qu’à ses tests de CHA et à ceux de ses alliés au contact pour les tests de négociation, de persuasion ou d’intimidation. Allez savoir pourquoi, sa simple présence donne de la force aux arguments de ses alliés..."
                },
                {
                    "rank": 2,
                    "name": "Tour de force",
                    "type": "Action Gratuite (G)",
                    "description": "Le barbare peut temporairement décupler ses ressources physiques pour faire usage d’une force prodigieuse. Il obtient un bonus de +10 sur un test de FOR (pas un jet de DM ou un test d’attaque), mais cela lui coûte 1d4° PV (à décider avant de lancer les dés). Enfin, le barbare peut désormais porter une chemise de mailles et utiliser toutes les capacités des voies de barbare auparavant autorisées avec une armure de cuir renforcé."
                },
                {
                    "rank": 3,
                    "name": "Attaque brutale",
                    "type": "Action Limitée (L)",
                    "description": "Le barbare effectue une puissante attaque au contact qui inflige +1d4° aux DM. À la place, il peut choisir de s’imposer un malus de ‑3 au test d’attaque pour obtenir +2d4° aux DM. Sur une attaque brutale réussie, il peut sacrifier 1d4° DM pour faire reculer de 3 m un adversaire de NC inférieur au rang atteint dans la voie, ou sacrifier 2d4° DM pour le renverser."
                },
                {
                    "rank": 4,
                    "name": "Force héroïque",
                    "type": "Passif",
                    "description": "Le barbare augmente sa FOR de +1. Désormais, il obtient un dé bonus aux tests de FOR."
                },
                {
                    "rank": 5,
                    "name": "Briseur d’os",
                    "type": "Passif",
                    "description": "Le barbare augmente de 1 point les chances d’obtenir un critique sur les attaques au contact (par exemple 19‑20 au lieu de 20). Lorsqu’il obtient un critique sur une attaque au contact, en plus des DM doublés, la cible est étourdie pendant 1 round. Enfin, le barbare peut désormais porter une cotte de mailles et utiliser toutes les capacités des voies de barbare auparavant autorisées avec une chemise de mailles."
                }
            ]
        },
        {
            "name": "Voie du Pagne",
            "abilities": [
                {
                    "rank": 1,
                    "name": "Vigueur",
                    "type": "Passif",
                    "description": "Le barbare est un athlète capable de prouesses physiques extraordinaires, il ajoute son rang + 2 aux tests de course, de saut ou d’escalade. De plus, il gagne 1 PV supplémentaire par rang atteint dans la voie."
                },
                {
                    "rank": 2,
                    "name": "Peau de pierre",
                    "type": "Passif",
                    "description": "Le barbare est particulièrement endurci, il encaisse les coups plutôt que de les esquiver. Il peut choisir de remplacer son AGI par sa CON pour calculer sa DEF (la limitation du bonus maximal en fonction de l’armure portée s’applique toujours, mais cette fois elle s’applique à la CON). Autrement (si son AGI est supérieure ou égale à sa CON), il reçoit +1 en DEF et ce bonus passe à +2 au rang 4."
                },
                {
                    "rank": 3,
                    "name": "Tatouages",
                    "type": "Passif",
                    "description": "Le barbare possède un tatouage magique qui améliore ses performances physiques ou mentales. Au choix : Taureau (+3 aux tests de FOR), ours (+3 aux tests de CON), panthère (+3 aux tests d’AGI), chouette (+3 aux tests de PER), loup (+3 aux tests de CHA), renard (+3 aux tests d’INT) ou serpent (+3 aux tests de VOL). De plus, lorsqu’il subit l’état étourdi, il est seulement ralenti. *Note : Ce bonus est un bonus de magie et ne se cumule pas avec les objets magiques.*",
                    "details": {
                        "options_tatouages": [
                            "Taureau (+3 FOR)",
                            "Ours (+3 CON)",
                            "Panthère (+3 AGI)",
                            "Chouette (+3 PER)",
                            "Loup (+3 CHA)",
                            "Renard (+3 INT)",
                            "Serpent (+3 VOL)"
                        ]
                    }
                },
                {
                    "rank": 4,
                    "name": "Constitution héroïque",
                    "type": "Passif",
                    "description": "Le barbare augmente sa valeur de CON de +1 et obtient un dé bonus aux tests de CON."
                },
                {
                    "rank": 5,
                    "name": "Peau d’acier",
                    "type": "Passif",
                    "description": "Le barbare ne sent plus la douleur et ignore les égratignures, il réduit tous les DM subis de 3 points (RD 3). Une attaque lui inflige toujours au minimum 1 DM."
                }
            ]
        },
        {
            "name": "Voie du Pourfendeur",
            "abilities": [
                {
                    "rank": 1,
                    "name": "Réflexes éclair",
                    "type": "Passif",
                    "description": "Le barbare ajoute son rang + 2 à tous les tests d’AGI destinés à esquiver (Explosion de feu, souffle, pièges, etc.). De plus, il gagne +3 en Init. et +1 en DEF. Le bonus de DEF passe à +2 au rang 5."
                },
                {
                    "rank": 2,
                    "name": "Charge",
                    "type": "Action Limitée (L)",
                    "description": "Le barbare se déplace en ligne droite entre 5 m et 10 m et effectue une attaque au contact avec un dé bonus et +1d4° aux DM. Il ne peut pas lancer une charge s’il est au contact d’un adversaire."
                },
                {
                    "rank": 3,
                    "name": "Enchaînement",
                    "type": "Passif / Action Gratuite",
                    "description": "Chaque fois que le barbare réduit un adversaire à 0 PV avec une attaque de contact, il bénéficie d’une action d’attaque gratuite sur un autre adversaire à son contact. Enchaînement ne peut pas être cumulé à un déchaînement d’acier ou une attaque tourbillon."
                },
                {
                    "rank": 4,
                    "name": "Déchaînement d’acier",
                    "type": "Action Limitée (L)",
                    "description": "Le barbare parcourt 10 m en ligne droite en dépassant autant d’ennemis qu’il le souhaite. Il porte une attaque avec un malus de ‑2 à chaque adversaire sur son passage. Il doit traverser l’espace occupé par ceux‑ci pour porter un coup, mais il ne peut terminer son déplacement à un endroit occupé par un ennemi."
                },
                {
                    "rank": 5,
                    "name": "Attaque tourbillon",
                    "type": "Action Limitée (L)",
                    "description": "Une fois par combat, le barbare tourne sur lui‑même en assénant des attaques à toutes les cibles au contact. Il inflige automatiquement des DM correspondant à l’arme utilisée (plus tous les bonus habituels) à toutes les cibles dans un rayon de 5 m autour de lui."
                }
            ]
        },
        {
            "name": "Voie du Primitif",
            "abilities": [
                {
                    "rank": 1,
                    "name": "Proche de la nature",
                    "type": "Passif",
                    "description": "Le barbare ajoute son rang + 2 à ses tests de survie (dont les tests de récupération) et de discrétion en milieu naturel. De plus, il gagne 1 PV supplémentaire."
                },
                {
                    "rank": 2,
                    "name": "Armure de vent",
                    "type": "Passif",
                    "description": "Lorsqu’il ne porte aucune armure, le barbare peut se relever par une action de mouvement et il obtient +2 en DEF. Ce bonus passe à +3 au rang 5. S’il porte une armure, il gagne seulement +1 en DEF."
                },
                {
                    "rank": 3,
                    "name": "Vigilance",
                    "type": "Passif",
                    "description": "Le barbare possède des sens très affûtés, il est difficile de le surprendre, il ajoute son rang + 2 à tous les tests effectués pour détecter les pièges mécaniques, magiques (ses poils se hérissent) ou les embuscades. Il devient immunisé aux Attaques sournoises d’un voleur ou à toute capacité similaire d’une créature de niveau inférieur au sien."
                },
                {
                    "rank": 4,
                    "name": "Résistance à la magie",
                    "type": "Action Gratuite (G)",
                    "description": "Le barbare devient capable de résister à la magie. Lorsqu’il est la cible d’un sort, une fois par round, il peut faire un test d’attaque magique opposé à celui du sort (si le sort n’en demande pas, faites‑en tout de même un à cette occasion). En cas de réussite, il n’en subit pas les effets. *Note : Si profil hybride capable de magie, subit un dé malus sur ce test.*"
                },
                {
                    "rank": 5,
                    "name": "Vitalité débordante",
                    "type": "Passif",
                    "description": "Le barbare guérit à une vitesse presque surnaturelle. Tant que son niveau actuel de PV est compris entre 1 et un tiers de son maximum, il récupère 1d4° PV par heure, de nuit comme de jour."
                }
            ]
        },
        {
            "name": "Voie de la Rage",
            "abilities": [
                {
                    "rank": 1,
                    "name": "Cri de guerre",
                    "type": "Action Gratuite (G)",
                    "description": "Une fois par combat, le barbare pousse un hurlement qui effraie ses adversaires dans un rayon de 10 m. Les adversaires dont la FOR est inférieure à celle du barbare subissent un dé malus à leurs tests d’attaque au contact durant leur prochain tour. De plus, le barbare est sans peur, il ajoute son rang + 2 à tous les tests de VOL destinés à résister à la peur."
                },
                {
                    "rank": 2,
                    "name": "Défier la mort",
                    "type": "Passif / Réaction",
                    "description": "Une fois par combat, lorsque le barbare subit des DM d’une attaque qui devrait l’amener à 0 PV, il peut réaliser un test de CON difficulté 10. En cas de réussite, il conserve 1 PV. S’il est enragé, la réussite est automatique."
                },
                {
                    "rank": 3,
                    "name": "Rage du berserk",
                    "type": "Action Limitée (L)",
                    "description": "Une fois par jour, le barbare entre dans une rage berserk pour le reste du combat, ce qui le rend particulièrement dangereux. Il obtient +1d4° DM sur ses attaques au contact, mais il subit ‑2 en DEF et ne peut fuir de son propre gré ou attaquer à distance. Enfin, il obtient un dé bonus pour tous les tests de VOL. S’il veut stopper la rage avant d’avoir éliminé tous les ennemis sur le terrain, le barbare doit réussir un test de VOL difficulté 15 (un seul essai, à la fin de son tour). S’il devient inconscient, la rage cesse. Le personnage peut entrer en rage une fois de plus par jour pour chaque capacité de rang 4 qu’il atteint dans une voie de barbare."
                },
                {
                    "rank": 4,
                    "name": "Même pas mal",
                    "type": "Passif / Réaction",
                    "description": "Une fois par combat, le barbare peut ignorer les DM d’un coup critique (il ne subit aucun DM) et il peut alors immédiatement entrer en Rage par une action gratuite."
                },
                {
                    "rank": 5,
                    "name": "Furie du berserk",
                    "type": "Action Limitée (L)",
                    "description": "Au lieu de la Rage du berserk, le barbare peut entrer en Furie du berserk, mais cela consomme deux utilisations de la rage. Cet état est similaire à la rage, mais le barbare ajoute 2d4° aux DM (au lieu de 1d4°) et subit ‑4 en DEF. La difficulté du test pour mettre prématurément fin à la furie est égale à 20."
                }
            ],
            "details": {
                "restrictions_generales": "La rage ne s'accorde avec aucune capacité nécessitant maîtrise et concentration (sorts, attaque sournoise, etc.). Non cumulable avec : Voie du maître d’armes (guerrier), Voie de l’escrime (barde), Voie de la maîtrise/méditation (moine), Voie du spadassin/assassin (voleur)."
            }
        }
    ]
}